LICENSE
README.md
setup.py
raster2polygon/__init__.py
raster2polygon/app.py
raster2polygon/extract.py
raster2polygon/get_polygons.py
raster2polygon/merge_polygons.py
raster2polygon/utils.py
raster2polygon.egg-info/PKG-INFO
raster2polygon.egg-info/SOURCES.txt
raster2polygon.egg-info/dependency_links.txt
raster2polygon.egg-info/requires.txt
raster2polygon.egg-info/top_level.txt
tests/test_app.py